AUTHORS.txt
LICENSE.txt
MANIFEST.in
conftest.py
setup.cfg
setup.py
docs/community.rst
docs/conf.py
docs/doc.rst
docs/downloads.rst
docs/index.rst
docs/reusablecomponents.rst
docs/_static/bblogo.png
docs/api/debug.rst
docs/api/delegates.rst
docs/api/dialogs.rst
docs/api/forms.rst
docs/api/gthreads.rst
docs/api/index.rst
docs/api/objectlist.rst
docs/api/proxy.rst
docs/api/test.rst
docs/api/utils.rst
docs/api/widgets.rst
docs/media/delegates.png
docs/media/pygtkhelpers_forms.png
docs/media/simpleform.png
examples/debug_trace.py
examples/forms.py
examples/icon-list.py
examples/list.py
examples/tree.py
examples/addressbook/address_form.ui
examples/addressbook/form.py
examples/addressbook/listing.py
examples/addressbook/person.py
examples/addressbook/view.py
examples/gtkbuilder/gtkbuilder_example.py
examples/gtkbuilder/interface.ui
examples/manual/d1.py
examples/manual/d2.py
examples/manual/d3.py
examples/manual/d4.py
examples/manual/d5.py
examples/manual/d6.py
examples/manual/d7.py
pygtkhelpers/__init__.py
pygtkhelpers/addons.py
pygtkhelpers/delegates.py
pygtkhelpers/forms.py
pygtkhelpers/gthreads.py
pygtkhelpers/proxy.py
pygtkhelpers/test.py
pygtkhelpers/utils.py
pygtkhelpers.egg-info/PKG-INFO
pygtkhelpers.egg-info/SOURCES.txt
pygtkhelpers.egg-info/dependency_links.txt
pygtkhelpers.egg-info/top_level.txt
pygtkhelpers/debug/__init__.py
pygtkhelpers/debug/console.py
pygtkhelpers/debug/dialogs.py
pygtkhelpers/ui/__init__.py
pygtkhelpers/ui/dialogs.py
pygtkhelpers/ui/widgets.py
pygtkhelpers/ui/objectlist/__init__.py
pygtkhelpers/ui/objectlist/column.py
pygtkhelpers/ui/objectlist/view.py
tests/__init__.py
tests/test_addons.py
tests/test_delegates.py
tests/test_forms.py
tests/test_gthreads.py
tests/test_proxy.py
tests/test_proxygroup.py
tests/test_utils.py
tests/data/black.png
tests/ui/test_dialogs.py
tests/ui/test_slave.ui
tests/ui/test_slave_builder_connect.ui
tests/ui/test_widgets.py
tests/ui/objectlist/__init__.py
tests/ui/objectlist/conftest.py
tests/ui/objectlist/test_api.py
tests/ui/objectlist/test_builder.py
tests/ui/objectlist/test_cell.py
tests/ui/objectlist/test_column.py
