Metadata-Version: 1.0
Name: pygtkhelpers
Version: 0.4.3
Summary: PyGTKHelpers is a library to assist the building of PyGTK applications.
Home-page: http://packages.python.org/pygtkhelpers
Author: Ali Afshar
Author-email: aafshar@gmail.com
License: LGPL-3.0
Platform: UNKNOWN
